{"is_source_file": true, "format": "JavaScript", "description": "This file contains helper functions for interacting with playlist-related API endpoints in a music streaming web frontend. It provides functions for listing, creating, retrieving, updating, deleting playlists, and adding/removing tracks from playlists, acting as a client-side API layer.", "external_files": ["./client"], "external_methods": ["http.get", "http.post", "http.patch", "http.delete"], "published": ["listPlaylists", "createPlaylist", "getPlaylist", "updatePlaylist", "deletePlaylist", "addTrackToPlaylist", "removeTrackFromPlaylist"], "classes": [], "methods": [{"name": "listPlaylists()", "description": "Fetches the current user's playlists, returning an array of playlist summaries.", "scope": "", "scopeKind": ""}, {"name": "createPlaylist(payload)", "description": "Creates a new playlist with provided fields such as name, description, and cover image.", "scope": "", "scopeKind": ""}, {"name": "getPlaylist(id)", "description": "Retrieves detailed information about a specific playlist by ID, including its tracks.", "scope": "", "scopeKind": ""}, {"name": "updatePlaylist(id, payload)", "description": "Updates playlist metadata and track membership via a PATCH request.", "scope": "", "scopeKind": ""}, {"name": "deletePlaylist(id)", "description": "Deletes a playlist by its ID.", "scope": "", "scopeKind": ""}, {"name": "addTrackToPlaylist(id, trackId)", "description": "Adds a specific track to a playlist.", "scope": "", "scopeKind": ""}, {"name": "removeTrackFromPlaylist(id, trackId)", "description": "Removes a specific track from a playlist.", "scope": "", "scopeKind": ""}], "calls": ["http.get", "http.post", "http.patch", "http.delete"], "search-terms": ["Playlist API", "playlists.js", "/api/playlists", "Playlist helper functions", "WebFrontend routes"], "state": 2, "file_id": 20, "knowledge_revision": 160, "git_revision": "997b66d903875af1f3b7d9532167842c13bfc6c7", "revision_history": [{"49": ""}, {"160": "997b66d903875af1f3b7d9532167842c13bfc6c7"}], "ctags": [{"_type": "tag", "name": "addTrackToPlaylist", "path": "/home/kavia/workspace/code-generation/music-streaming-service-21915-22054/WebFrontend/src/api/playlists.js", "pattern": "/^export async function addTrackToPlaylist(id, trackId) {$/", "language": "JavaScript", "kind": "function", "signature": "(id, trackId)"}, {"_type": "tag", "name": "createPlaylist", "path": "/home/kavia/workspace/code-generation/music-streaming-service-21915-22054/WebFrontend/src/api/playlists.js", "pattern": "/^export async function createPlaylist(payload) {$/", "language": "JavaScript", "kind": "function", "signature": "(payload)"}, {"_type": "tag", "name": "deletePlaylist", "path": "/home/kavia/workspace/code-generation/music-streaming-service-21915-22054/WebFrontend/src/api/playlists.js", "pattern": "/^export async function deletePlaylist(id) {$/", "language": "JavaScript", "kind": "function", "signature": "(id)"}, {"_type": "tag", "name": "getPlaylist", "path": "/home/kavia/workspace/code-generation/music-streaming-service-21915-22054/WebFrontend/src/api/playlists.js", "pattern": "/^export async function getPlaylist(id) {$/", "language": "JavaScript", "kind": "function", "signature": "(id)"}, {"_type": "tag", "name": "listPlaylists", "path": "/home/kavia/workspace/code-generation/music-streaming-service-21915-22054/WebFrontend/src/api/playlists.js", "pattern": "/^export async function listPlaylists() {$/", "language": "JavaScript", "kind": "function", "signature": "()"}, {"_type": "tag", "name": "removeTrackFromPlaylist", "path": "/home/kavia/workspace/code-generation/music-streaming-service-21915-22054/WebFrontend/src/api/playlists.js", "pattern": "/^export async function removeTrackFromPlaylist(id, trackId) {$/", "language": "JavaScript", "kind": "function", "signature": "(id, trackId)"}, {"_type": "tag", "name": "updatePlaylist", "path": "/home/kavia/workspace/code-generation/music-streaming-service-21915-22054/WebFrontend/src/api/playlists.js", "pattern": "/^export async function updatePlaylist(id, payload) {$/", "language": "JavaScript", "kind": "function", "signature": "(id, payload)"}], "hash": "1781e515c79fc8864fc0196ac23ac536", "format-version": 4, "code-base-name": "WebFrontend", "filename": "WebFrontend/src/api/playlists.js"}